gddsitu/__init__.py
gdDSITU-0.0.1.dist-info/LICENCE.txt
gdDSITU-0.0.1.dist-info/METADATA
gdDSITU-0.0.1.dist-info/WHEEL
gdDSITU-0.0.1.dist-info/top_level.txt
gdDSITU-0.0.1.dist-info/RECORD
